qdsim/_CapacitanceQDArray.py
qdsim/_QuantumDotDevice.py
qdsim/_QuantumDotSimulator.py
qdsim/__init__.py
qdsim/_auxiliaryfunctions.py
qdsim/_noisefunctions.py
qdsim/_plotCSD.py
QDsim-1.0.1.dist-info/LICENSE
QDsim-1.0.1.dist-info/METADATA
QDsim-1.0.1.dist-info/WHEEL
QDsim-1.0.1.dist-info/top_level.txt
QDsim-1.0.1.dist-info/RECORD
