Metadata-Version: 2.1
Name: QDsim
Version: 1.0.1
Summary: QDsim is an user-friendly tool that quickly simulates charge stability diagrams for large quantum dot devices (even 100+ dots).
Author: Charles Renshaw-Whitman, Vinicius F. Hernandes, Eliška Greplová
Author-email: Valentina Gualtieri <v.gualtieri@tudelft.nl>
Project-URL: Homepage, https://gitlab.com/QMAI/papers/qdsim/
Project-URL: Issues, https://gitlab.com/QMAI/papers/qdsim/issues
Classifier: Programming Language :: Python :: 3
Classifier: License :: OSI Approved :: MIT License
Classifier: Operating System :: OS Independent
Requires-Python: >=3.9
License-File: LICENSE
